django_dynamic_fixtures-0.2.1.dist-info/DESCRIPTION.rst
django_dynamic_fixtures-0.2.1.dist-info/METADATA
django_dynamic_fixtures-0.2.1.dist-info/RECORD
django_dynamic_fixtures-0.2.1.dist-info/WHEEL
django_dynamic_fixtures-0.2.1.dist-info/metadata.json
django_dynamic_fixtures-0.2.1.dist-info/top_level.txt
dynamic_fixtures/__init__.py
dynamic_fixtures/fixtures/__init__.py
dynamic_fixtures/fixtures/basefixture.py
dynamic_fixtures/fixtures/exceptions.py
dynamic_fixtures/fixtures/loader.py
dynamic_fixtures/fixtures/runner.py
dynamic_fixtures/management/__init__.py
dynamic_fixtures/management/commands/__init__.py
dynamic_fixtures/management/commands/load_dynamic_fixtures.py
