Metadata-Version: 2.0
Name: django-dynamic-fixtures
Version: 0.2.1
Summary: Install Dynamic Django fixtures.
Home-page: https://github.com/Peter-Slump/django-dynamic-fixtures
Author: Peter Slump
Author-email: peter@yarf.nl
License: MIT
Platform: UNKNOWN
Classifier: Development Status :: 5 - Production/Stable
Classifier: Environment :: Console
Classifier: Framework :: Django :: 1.8
Classifier: Framework :: Django :: 1.9
Classifier: Framework :: Django :: 1.10
Classifier: Framework :: Django :: 1.11
Classifier: Framework :: Django :: 2.0
Classifier: Intended Audience :: Developers
Classifier: License :: OSI Approved :: MIT License
Classifier: Programming Language :: Python :: 2.7
Classifier: Programming Language :: Python :: 3.3
Classifier: Programming Language :: Python :: 3.4
Classifier: Programming Language :: Python :: 3.5
Classifier: Topic :: Software Development :: Testing
Requires-Dist: Django (>=1.7)
Provides-Extra: dev
Requires-Dist: bumpversion (==0.5.3); extra == 'dev'
Requires-Dist: twine (==1.9.1); extra == 'dev'
Provides-Extra: doc
Requires-Dist: Sphinx (==1.4.4); extra == 'doc'
Requires-Dist: sphinx-autobuild (==0.6.0); extra == 'doc'
